{
  "dashboard": {
    "title": "Day 0-1 Launch Monitoring",
    "tags": ["launch", "day-0", "monitoring", "sre"],
    "timezone": "browser",
    "schemaVersion": 38,
    "version": 1,
    "refresh": "10s",
    "time": {
      "from": "now-2h",
      "to": "now"
    },
    "panels": [
      {
        "id": 1,
        "title": "🚨 Critical Health Indicators",
        "type": "row",
        "gridPos": {"h": 1, "w": 24, "x": 0, "y": 0}
      },
      {
        "id": 2,
        "title": "Service Uptime",
        "type": "stat",
        "gridPos": {"h": 4, "w": 6, "x": 0, "y": 1},
        "targets": [
          {
            "expr": "up{job=~\".*payment.*\"}",
            "legendFormat": "{{instance}}"
          }
        ],
        "options": {
          "colorMode": "background",
          "graphMode": "none",
          "textMode": "value_and_name"
        },
        "fieldConfig": {
          "defaults": {
            "thresholds": {
              "mode": "absolute",
              "steps": [
                {"value": 0, "color": "red"},
                {"value": 1, "color": "green"}
              ]
            },
            "unit": "short",
            "mappings": [
              {"options": {"0": {"text": "DOWN"}}, "type": "value"},
              {"options": {"1": {"text": "UP"}}, "type": "value"}
            ]
          }
        }
      },
      {
        "id": 3,
        "title": "Error Rate (5min)",
        "type": "stat",
        "gridPos": {"h": 4, "w": 6, "x": 6, "y": 1},
        "targets": [
          {
            "expr": "sum(rate(http_requests_total{status=~\"5..\"}[5m])) / sum(rate(http_requests_total[5m])) * 100",
            "legendFormat": "Error Rate"
          }
        ],
        "options": {
          "colorMode": "background",
          "graphMode": "area",
          "textMode": "value"
        },
        "fieldConfig": {
          "defaults": {
            "thresholds": {
              "mode": "absolute",
              "steps": [
                {"value": 0, "color": "green"},
                {"value": 1, "color": "yellow"},
                {"value": 5, "color": "red"}
              ]
            },
            "unit": "percent",
            "decimals": 2
          }
        }
      },
      {
        "id": 4,
        "title": "P95 Latency",
        "type": "stat",
        "gridPos": {"h": 4, "w": 6, "x": 12, "y": 1},
        "targets": [
          {
            "expr": "histogram_quantile(0.95, sum(rate(http_request_duration_seconds_bucket[5m])) by (le))",
            "legendFormat": "P95 Latency"
          }
        ],
        "options": {
          "colorMode": "background",
          "graphMode": "area",
          "textMode": "value"
        },
        "fieldConfig": {
          "defaults": {
            "thresholds": {
              "mode": "absolute",
              "steps": [
                {"value": 0, "color": "green"},
                {"value": 1, "color": "yellow"},
                {"value": 5, "color": "red"}
              ]
            },
            "unit": "s"
          }
        }
      },
      {
        "id": 5,
        "title": "Active Alerts",
        "type": "stat",
        "gridPos": {"h": 4, "w": 6, "x": 18, "y": 1},
        "targets": [
          {
            "expr": "count(ALERTS{alertstate=\"firing\"})",
            "legendFormat": "Firing Alerts"
          }
        ],
        "options": {
          "colorMode": "background",
          "graphMode": "none",
          "textMode": "value"
        },
        "fieldConfig": {
          "defaults": {
            "thresholds": {
              "mode": "absolute",
              "steps": [
                {"value": 0, "color": "green"},
                {"value": 1, "color": "yellow"},
                {"value": 3, "color": "red"}
              ]
            },
            "unit": "short"
          }
        }
      },
      {
        "id": 6,
        "title": "📊 Request Volume & Performance",
        "type": "row",
        "gridPos": {"h": 1, "w": 24, "x": 0, "y": 5}
      },
      {
        "id": 7,
        "title": "Request Rate (RPS)",
        "type": "graph",
        "gridPos": {"h": 8, "w": 12, "x": 0, "y": 6},
        "targets": [
          {
            "expr": "sum(rate(http_requests_total[1m])) by (method, status)",
            "legendFormat": "{{method}} {{status}}"
          }
        ],
        "yAxes": [
          {"label": "Requests/sec", "unit": "reqps"},
          {"show": false}
        ],
        "legend": {
          "show": true,
          "values": true,
          "current": true
        }
      },
      {
        "id": 8,
        "title": "Response Time Distribution",
        "type": "graph",
        "gridPos": {"h": 8, "w": 12, "x": 12, "y": 6},
        "targets": [
          {
            "expr": "histogram_quantile(0.50, sum(rate(http_request_duration_seconds_bucket[5m])) by (le))",
            "legendFormat": "P50"
          },
          {
            "expr": "histogram_quantile(0.95, sum(rate(http_request_duration_seconds_bucket[5m])) by (le))",
            "legendFormat": "P95"
          },
          {
            "expr": "histogram_quantile(0.99, sum(rate(http_request_duration_seconds_bucket[5m])) by (le))",
            "legendFormat": "P99"
          }
        ],
        "yAxes": [
          {"label": "Response Time", "unit": "s"},
          {"show": false}
        ]
      },
      {
        "id": 9,
        "title": "💳 Payment System Health",
        "type": "row",
        "gridPos": {"h": 1, "w": 24, "x": 0, "y": 14}
      },
      {
        "id": 10,
        "title": "Payment Success Rate",
        "type": "graph",
        "gridPos": {"h": 8, "w": 8, "x": 0, "y": 15},
        "targets": [
          {
            "expr": "sum(rate(payment_init_total{result=\"success\"}[5m])) by (provider) / sum(rate(payment_init_total[5m])) by (provider)",
            "legendFormat": "{{provider}}"
          }
        ],
        "yAxes": [
          {"label": "Success Rate", "unit": "percentunit", "min": 0, "max": 1},
          {"show": false}
        ],
        "alert": {
          "conditions": [
            {
              "evaluator": {"params": [0.95], "type": "lt"},
              "operator": {"type": "and"},
              "query": {"params": ["A", "5m", "now"]},
              "reducer": {"params": [], "type": "avg"},
              "type": "query"
            }
          ],
          "executionErrorState": "alerting",
          "frequency": "1m",
          "handler": 1,
          "name": "Payment Success Rate Low",
          "noDataState": "no_data"
        }
      },
      {
        "id": 11,
        "title": "Webhook Processing",
        "type": "graph",
        "gridPos": {"h": 8, "w": 8, "x": 8, "y": 15},
        "targets": [
          {
            "expr": "sum(rate(webhook_ok_total[5m])) by (provider)",
            "legendFormat": "{{provider}} - Success"
          },
          {
            "expr": "sum(rate(payment_webhook_total{result=\"error\"}[5m])) by (provider)",
            "legendFormat": "{{provider}} - Error"
          }
        ],
        "yAxes": [
          {"label": "Webhooks/sec", "unit": "reqps"},
          {"show": false}
        ]
      },
      {
        "id": 12,
        "title": "Reconciliation Status",
        "type": "stat",
        "gridPos": {"h": 8, "w": 8, "x": 16, "y": 15},
        "targets": [
          {
            "expr": "sum(reconciliation_stuck_total)",
            "legendFormat": "Stuck Payments"
          },
          {
            "expr": "max(payment_stuck_minutes)",
            "legendFormat": "Oldest (min)"
          }
        ],
        "options": {
          "colorMode": "background",
          "graphMode": "area",
          "textMode": "value_and_name"
        },
        "fieldConfig": {
          "defaults": {
            "thresholds": {
              "mode": "absolute",
              "steps": [
                {"value": 0, "color": "green"},
                {"value": 5, "color": "yellow"},
                {"value": 10, "color": "red"}
              ]
            },
            "unit": "short"
          }
        }
      },
      {
        "id": 13,
        "title": "📧 Notification System",
        "type": "row",
        "gridPos": {"h": 1, "w": 24, "x": 0, "y": 23}
      },
      {
        "id": 14,
        "title": "Notification Backlog",
        "type": "graph",
        "gridPos": {"h": 8, "w": 8, "x": 0, "y": 24},
        "targets": [
          {
            "expr": "notification_outbox_backlog{status=\"ready\"}",
            "legendFormat": "Ready"
          },
          {
            "expr": "notification_outbox_backlog{status=\"claimed\"}",
            "legendFormat": "Claimed"
          },
          {
            "expr": "notification_outbox_backlog{status=\"delayed\"}",
            "legendFormat": "Delayed"
          }
        ],
        "yAxes": [
          {"label": "Messages", "unit": "short"},
          {"show": false}
        ],
        "alert": {
          "conditions": [
            {
              "evaluator": {"params": [1000], "type": "gt"},
              "operator": {"type": "and"},
              "query": {"params": ["A", "5m", "now"]},
              "reducer": {"params": [], "type": "last"},
              "type": "query"
            }
          ],
          "executionErrorState": "alerting",
          "frequency": "1m",
          "handler": 1,
          "name": "Notification Backlog High",
          "noDataState": "no_data"
        }
      },
      {
        "id": 15,
        "title": "Notification Dispatch Rate",
        "type": "graph",
        "gridPos": {"h": 8, "w": 8, "x": 8, "y": 24},
        "targets": [
          {
            "expr": "sum(rate(notification_dispatch_total{status=\"sent\"}[5m])) by (channel)",
            "legendFormat": "{{channel}} - Sent"
          },
          {
            "expr": "sum(rate(notification_dispatch_total{status=\"failed\"}[5m])) by (channel)",
            "legendFormat": "{{channel}} - Failed"
          }
        ],
        "yAxes": [
          {"label": "Notifications/sec", "unit": "reqps"},
          {"show": false}
        ]
      },
      {
        "id": 16,
        "title": "Visibility Timeout Resets",
        "type": "stat",
        "gridPos": {"h": 8, "w": 8, "x": 16, "y": 24},
        "targets": [
          {
            "expr": "increase(notification_stuck_reset_total[1h])",
            "legendFormat": "Last Hour"
          },
          {
            "expr": "increase(notification_stuck_reset_total[24h])",
            "legendFormat": "Last 24h"
          }
        ],
        "options": {
          "colorMode": "background",
          "graphMode": "area",
          "textMode": "value_and_name"
        },
        "fieldConfig": {
          "defaults": {
            "thresholds": {
              "mode": "absolute",
              "steps": [
                {"value": 0, "color": "green"},
                {"value": 10, "color": "yellow"},
                {"value": 50, "color": "red"}
              ]
            },
            "unit": "short"
          }
        }
      },
      {
        "id": 17,
        "title": "☸️ Kubernetes Health",
        "type": "row",
        "gridPos": {"h": 1, "w": 24, "x": 0, "y": 32}
      },
      {
        "id": 18,
        "title": "Pod Restarts (24h)",
        "type": "stat",
        "gridPos": {"h": 4, "w": 6, "x": 0, "y": 33},
        "targets": [
          {
            "expr": "increase(kube_pod_container_status_restarts_total{pod=~\".*payment.*\"}[24h])",
            "legendFormat": "{{pod}}"
          }
        ],
        "options": {
          "colorMode": "background",
          "graphMode": "none",
          "textMode": "value_and_name"
        },
        "fieldConfig": {
          "defaults": {
            "thresholds": {
              "mode": "absolute",
              "steps": [
                {"value": 0, "color": "green"},
                {"value": 1, "color": "yellow"},
                {"value": 5, "color": "red"}
              ]
            },
            "unit": "short"
          }
        }
      },
      {
        "id": 19,
        "title": "Probe Failures (1h)",
        "type": "stat",
        "gridPos": {"h": 4, "w": 6, "x": 6, "y": 33},
        "targets": [
          {
            "expr": "increase(prober_probe_total{result=\"failure\"}[1h])",
            "legendFormat": "{{instance}}"
          }
        ],
        "options": {
          "colorMode": "background",
          "graphMode": "none",
          "textMode": "value_and_name"
        },
        "fieldConfig": {
          "defaults": {
            "thresholds": {
              "mode": "absolute",
              "steps": [
                {"value": 0, "color": "green"},
                {"value": 1, "color": "yellow"},
                {"value": 10, "color": "red"}
              ]
            },
            "unit": "short"
          }
        }
      },
      {
        "id": 20,
        "title": "Memory Usage",
        "type": "graph",
        "gridPos": {"h": 8, "w": 12, "x": 12, "y": 33},
        "targets": [
          {
            "expr": "container_memory_usage_bytes{pod=~\".*payment.*\"} / container_spec_memory_limit_bytes * 100",
            "legendFormat": "{{pod}}"
          }
        ],
        "yAxes": [
          {"label": "Memory %", "unit": "percent", "min": 0, "max": 100},
          {"show": false}
        ]
      },
      {
        "id": 21,
        "title": "CPU Usage",
        "type": "graph",
        "gridPos": {"h": 8, "w": 12, "x": 0, "y": 37},
        "targets": [
          {
            "expr": "rate(container_cpu_usage_seconds_total{pod=~\".*payment.*\"}[5m]) * 100",
            "legendFormat": "{{pod}}"
          }
        ],
        "yAxes": [
          {"label": "CPU %", "unit": "percent"},
          {"show": false}
        ]
      },
      {
        "id": 22,
        "title": "🔍 Tracing & Debugging",
        "type": "row",
        "gridPos": {"h": 1, "w": 24, "x": 0, "y": 45}
      },
      {
        "id": 23,
        "title": "Request ID Propagation",
        "type": "stat",
        "gridPos": {"h": 4, "w": 6, "x": 0, "y": 46},
        "targets": [
          {
            "expr": "sum(rate(http_requests_total{has_request_id=\"true\"}[5m])) / sum(rate(http_requests_total[5m])) * 100",
            "legendFormat": "With Request ID"
          }
        ],
        "options": {
          "colorMode": "background",
          "graphMode": "area",
          "textMode": "value"
        },
        "fieldConfig": {
          "defaults": {
            "thresholds": {
              "mode": "absolute",
              "steps": [
                {"value": 0, "color": "red"},
                {"value": 90, "color": "yellow"},
                {"value": 99, "color": "green"}
              ]
            },
            "unit": "percent"
          }
        }
      },
      {
        "id": 24,
        "title": "Trace Context Propagation",
        "type": "stat",
        "gridPos": {"h": 4, "w": 6, "x": 6, "y": 46},
        "targets": [
          {
            "expr": "sum(rate(http_requests_total{has_traceparent=\"true\"}[5m])) / sum(rate(http_requests_total[5m])) * 100",
            "legendFormat": "With traceparent"
          }
        ],
        "options": {
          "colorMode": "background",
          "graphMode": "area",
          "textMode": "value"
        },
        "fieldConfig": {
          "defaults": {
            "thresholds": {
              "mode": "absolute",
              "steps": [
                {"value": 0, "color": "red"},
                {"value": 50, "color": "yellow"},
                {"value": 80, "color": "green"}
              ]
            },
            "unit": "percent"
          }
        }
      },
      {
        "id": 25,
        "title": "Log Volume by Level",
        "type": "graph",
        "gridPos": {"h": 8, "w": 12, "x": 12, "y": 46},
        "targets": [
          {
            "expr": "sum(rate(log_messages_total[5m])) by (level)",
            "legendFormat": "{{level}}"
          }
        ],
        "yAxes": [
          {"label": "Logs/sec", "unit": "reqps"},
          {"show": false}
        ]
      },
      {
        "id": 26,
        "title": "📋 Launch Checklist Status",
        "type": "row",
        "gridPos": {"h": 1, "w": 24, "x": 0, "y": 54}
      },
      {
        "id": 27,
        "title": "Pre-Launch Audit Results",
        "type": "table",
        "gridPos": {"h": 8, "w": 24, "x": 0, "y": 55},
        "targets": [
          {
            "expr": "audit_check_status",
            "format": "table",
            "legendFormat": ""
          }
        ],
        "options": {
          "showHeader": true
        },
        "fieldConfig": {
          "defaults": {
            "custom": {
              "displayMode": "color-background"
            },
            "thresholds": {
              "mode": "absolute",
              "steps": [
                {"value": 0, "color": "red"},
                {"value": 1, "color": "green"}
              ]
            }
          }
        }
      }
    ],
    "annotations": {
      "list": [
        {
          "name": "Deployments",
          "datasource": "prometheus",
          "enable": true,
          "expr": "changes(up[5m]) > 0",
          "iconColor": "blue",
          "titleFormat": "Deployment",
          "textFormat": "Service {{instance}} deployment detected"
        },
        {
          "name": "Alerts",
          "datasource": "prometheus",
          "enable": true,
          "expr": "ALERTS{alertstate=\"firing\"}",
          "iconColor": "red",
          "titleFormat": "Alert: {{alertname}}",
          "textFormat": "{{summary}}"
        }
      ]
    },
    "templating": {
      "list": [
        {
          "name": "environment",
          "type": "query",
          "query": "label_values(up, environment)",
          "current": {
            "value": "production",
            "text": "production"
          }
        },
        {
          "name": "instance",
          "type": "query",
          "query": "label_values(up{environment=\"$environment\"}, instance)",
          "multi": true,
          "includeAll": true
        }
      ]
    }
  }
}
